lib_roman/__init__.py
lib_roman/get_roman_numbers.py
lib_roman-0.0.1.dist-info/METADATA
lib_roman-0.0.1.dist-info/WHEEL
lib_roman-0.0.1.dist-info/top_level.txt
lib_roman-0.0.1.dist-info/RECORD
